Metadata-Version: 2.4
Name: zyte-spider-templates
Version: 0.12.0
Summary: Spider templates for automatic crawlers.
Home-page: https://github.com/zytedata/zyte-spider-templates
Author: Zyte Group Ltd
Author-email: info@zyte.com
Classifier: Development Status :: 3 - Alpha
Classifier: Intended Audience :: Developers
Classifier: License :: OSI Approved :: BSD License
Classifier: Operating System :: OS Independent
Classifier: Programming Language :: Python :: 3
Classifier: Programming Language :: Python :: 3.9
Classifier: Programming Language :: Python :: 3.10
Classifier: Programming Language :: Python :: 3.11
Classifier: Programming Language :: Python :: 3.12
Classifier: Programming Language :: Python :: 3.13
License-File: LICENSE
Requires-Dist: duplicate-url-discarder>=0.2.0
Requires-Dist: duplicate-url-discarder-rules>=2024.11.05
Requires-Dist: extruct>=0.18.0
Requires-Dist: feedparser>=6.0.11
Requires-Dist: form2request>=0.2.0
Requires-Dist: formasaurus>=0.10.0
Requires-Dist: jmespath>=0.9.5
Requires-Dist: pydantic>=2.1
Requires-Dist: requests>=2.31.0
Requires-Dist: scrapinghub>=2.4.0
Requires-Dist: scrapy>=2.11.0
Requires-Dist: scrapy-poet>=0.24.0
Requires-Dist: scrapy-spider-metadata>=0.2.0
Requires-Dist: scrapy-zyte-api[provider]>=0.25.0
Requires-Dist: web-poet>=0.17.1
Requires-Dist: xtractmime>=0.2.1
Requires-Dist: zyte-common-items>=0.26.2
Dynamic: author
Dynamic: author-email
Dynamic: classifier
Dynamic: description
Dynamic: description-content-type
Dynamic: home-page
Dynamic: license-file
Dynamic: requires-dist
Dynamic: summary
